dome/__init__.py
e_dome-2.0.3.dist-info/METADATA
e_dome-2.0.3.dist-info/WHEEL
e_dome-2.0.3.dist-info/entry_points.txt
e_dome-2.0.3.dist-info/top_level.txt
e_dome-2.0.3.dist-info/RECORD
