Metadata-Version: 2.4
Name: e-dome
Version: 2.0.3
Summary: DOME - Natural Language Programming
Home-page: https://github.com/yourusername/dome
Author: e-dome.dev
Author-email: contact@e-dome.dev
Project-URL: Bug Tracker, https://github.com/yourusername/dome/issues
Project-URL: Source Code, https://github.com/yourusername/dome
Keywords: natural-language-programming,code-generation,nlp,python
Classifier: Development Status :: 4 - Beta
Classifier: Intended Audience :: Developers
Classifier: License :: OSI Approved :: MIT License
Classifier: Operating System :: OS Independent
Classifier: Programming Language :: Python :: 3
Classifier: Programming Language :: Python :: 3.7
Classifier: Programming Language :: Python :: 3.8
Classifier: Programming Language :: Python :: 3.9
Classifier: Programming Language :: Python :: 3.10
Classifier: Programming Language :: Python :: 3.11
Classifier: Programming Language :: Python :: 3.12
Classifier: Topic :: Software Development :: Code Generators
Classifier: Topic :: Software Development :: Interpreters
Classifier: Topic :: Scientific/Engineering :: Artificial Intelligence
Requires-Python: >=3.7
Requires-Dist: requests>=2.25.0
Provides-Extra: full
Requires-Dist: pandas>=1.3.0; extra == "full"
Requires-Dist: numpy>=1.20.0; extra == "full"
Requires-Dist: matplotlib>=3.3.0; extra == "full"
Requires-Dist: seaborn>=0.11.0; extra == "full"
Requires-Dist: scikit-learn>=1.0.0; extra == "full"
Dynamic: author
Dynamic: author-email
Dynamic: classifier
Dynamic: description
Dynamic: description-content-type
Dynamic: home-page
Dynamic: keywords
Dynamic: project-url
Dynamic: provides-extra
Dynamic: requires-dist
Dynamic: requires-python
Dynamic: summary
